ivygc/__init__.py
ivygc/__main__.py
ivygc/acdsee.py
ivygc/app.py
ivygc/bg.jpg
ivygc/clean.txt
ivygc/common.py
ivygc/dotlang.py
ivygc/gc.txt
ivygc/gc2-ivy-torch.txt
ivygc/gc2-ivy.txt
ivygc/gc2-torch.txt
ivygc/graphcompiler.py
ivygc/py.grammar
ivygc/status.jpg
ivygc/unclean.txt
ivygc-0.0.2.dist-info/LICENSE
ivygc-0.0.2.dist-info/METADATA
ivygc-0.0.2.dist-info/WHEEL
ivygc-0.0.2.dist-info/top_level.txt
ivygc-0.0.2.dist-info/RECORD
