Metadata-Version: 2.1
Name: ivygc
Version: 0.0.2
Summary: Ivy's GC
Author-email: yusef <yusef314159@gmail.com>
License: Copyright (c) 2018 The Python Packaging Authority        
Project-URL: Homepage, https://github.com/mexusef/ivygc
Project-URL: Bug Tracker, https://github.com/mexusef/ivygc/issues
Classifier: Programming Language :: Python :: 3
Classifier: License :: OSI Approved :: MIT License
Classifier: Operating System :: OS Independent
Requires-Python: >=3.9
License-File: LICENSE
Requires-Dist: PyQt5 (~=5.15.6)
Requires-Dist: QScintilla (~=2.13.2)
Requires-Dist: graphviz (~=0.20)
Requires-Dist: lark-parser
